warehouser/__init__.py
warehouser/base_manager.py
warehouser/const.py
warehouser/core.py
warehouser/db_config.py
warehouser/log.py
warehouser/manager.py
warehouser/playground.py
warehouser/reflection.py
warehouser/sql_builder.py
warehouser/sql_util.py
warehouser/util.py
warehouser-0.3.8.dist-info/licenses/LICENSE
warehouser-0.3.8.dist-info/METADATA
warehouser-0.3.8.dist-info/WHEEL
warehouser-0.3.8.dist-info/top_level.txt
warehouser-0.3.8.dist-info/RECORD
