Metadata-Version: 2.4
Name: warehouser
Version: 0.3.8
Summary: Medical Procurement of Ukraine DataLakeHouse project.
Author: Vasyl Tsiura
Classifier: Programming Language :: Python :: 3
Requires-Python: >=3.10.12
License-File: LICENSE
Requires-Dist: pandas>=2.2.3
Requires-Dist: funcy>=2.0
Requires-Dist: pytz
Requires-Dist: SQLAlchemy>=2.0.35
Requires-Dist: psycopg2-binary>=2.9.9
Requires-Dist: PyMySQL>=1.1.1
Requires-Dist: cryptography>=43.0.1
Requires-Dist: doris-alchemy>=0.2.3
Requires-Dist: trent>=0.2.7
Dynamic: license-file
